traceint/__init__.py
traceint/cancel.py
traceint/seat_book.py
traceint/seat_reserve.py
traceint/sign.py
traceint/utils/__init__.py
traceint/utils/io_func.py
traceint/utils/pass_func.py
traceint/utils/request.py
traceint/utils/utils.py
traceint/utils/wait_func.py
traceint-1.3.6.dist-info/LICENSE
traceint-1.3.6.dist-info/METADATA
traceint-1.3.6.dist-info/WHEEL
traceint-1.3.6.dist-info/top_level.txt
traceint-1.3.6.dist-info/RECORD
