Metadata-Version: 2.1
Name: traceint
Version: 1.3.6
Summary: integrated assistance of traceint
Home-page: https://github.com/yuzheng14/tracient_book_sduwh
Author: yuzheng14
Author-email: yuzheng14@yuzheng14.com
License: UNKNOWN
Platform: UNKNOWN
Classifier: Programming Language :: Python :: 3
Classifier: Operating System :: OS Independent
Requires-Dist: ddddocr (>=1.1.0)
Requires-Dist: requests (>=2.26.0)
Requires-Dist: websocket-client (>=1.2.3)
